Compiled from "Unsage.java"
public class com.viki.other.Unsage {
  public com.viki.other.Unsage();
    Code:
       0: aload_0
       1: invokespecial #1                  // Method java/lang/Object."<init>":()V
       4: return

  public static void main(java.lang.String[]) throws java.lang.NoSuchFieldException, java.lang.IllegalAccessException, java.lang.InstantiationException;
    Code:
       0: ldc           #2                  // class sun/misc/Unsafe
       2: ldc           #3                  // String theUnsafe
       4: invokevirtual #4                  // Method java/lang/Class.getDeclaredField:(Ljava/lang/String;)Ljava/lang/reflect/Field;
       7: astore_1
       8: aload_1
       9: iconst_1
      10: invokevirtual #5                  // Method java/lang/reflect/Field.setAccessible:(Z)V
      13: aload_1
      14: aconst_null
      15: invokevirtual #6                  // Method java/lang/reflect/Field.get:(Ljava/lang/Object;)Ljava/lang/Object;
      18: checkcast     #2                  // class sun/misc/Unsafe
      21: astore_2
      22: aload_2
      23: ldc           #7                  // class com/viki/other/Unsage$Player
      25: invokevirtual #8                  // Method sun/misc/Unsafe.allocateInstance:(Ljava/lang/Class;)Ljava/lang/Object;
      28: checkcast     #7                  // class com/viki/other/Unsage$Player
      31: astore_3
      32: getstatic     #9                  // Field java/lang/System.out:Ljava/io/PrintStream;
      35: new           #10                 // class java/lang/StringBuilder
      38: dup
      39: invokespecial #11                 // Method java/lang/StringBuilder."<init>":()V
      42: ldc           #12                 // String age =
      44: invokevirtual #13                 // Method java/lang/StringBuilder.append:(Ljava/lang/String;)Ljava/lang/StringBuilder;
      47: aload_3
      48: invokevirtual #14                 // Method com/viki/other/Unsage$Player.getAge:()I
      51: invokevirtual #15                 // Method java/lang/StringBuilder.append:(I)Ljava/lang/StringBuilder;
      54: invokevirtual #16                 // Method java/lang/StringBuilder.toString:()Ljava/lang/String;
      57: invokevirtual #17                 // Method java/io/PrintStream.println:(Ljava/lang/String;)V
      60: aload_3
      61: bipush        100
      63: invokevirtual #18                 // Method com/viki/other/Unsage$Player.setAge:(I)V
      66: getstatic     #9                  // Field java/lang/System.out:Ljava/io/PrintStream;
      69: new           #10                 // class java/lang/StringBuilder
      72: dup
      73: invokespecial #11                 // Method java/lang/StringBuilder."<init>":()V
      76: ldc           #12                 // String age =
      78: invokevirtual #13                 // Method java/lang/StringBuilder.append:(Ljava/lang/String;)Ljava/lang/StringBuilder;
      81: aload_3
      82: invokevirtual #14                 // Method com/viki/other/Unsage$Player.getAge:()I
      85: invokevirtual #15                 // Method java/lang/StringBuilder.append:(I)Ljava/lang/StringBuilder;
      88: invokevirtual #16                 // Method java/lang/StringBuilder.toString:()Ljava/lang/String;
      91: invokevirtual #17                 // Method java/io/PrintStream.println:(Ljava/lang/String;)V
      94: return
}
